panelvar/__init__.py
panelvar/__version__.py
panelvar/dynamic_panel_model.py
panelvar/irf.py
panelvar/model_summary.py
panelvar/panel_data.py
panelvar/pvar_module.so
panelvar/regression.py
panelvar-0.0.2.dist-info/LICENSE
panelvar-0.0.2.dist-info/METADATA
panelvar-0.0.2.dist-info/WHEEL
panelvar-0.0.2.dist-info/top_level.txt
panelvar-0.0.2.dist-info/RECORD
